shuke_ai/main.py
shuke_ai/pyarmor_runtime_000000/__init__.py
shuke_ai/pyarmor_runtime_000000/pyarmor_runtime.so
shuke_ai-0.3.5.dist-info/METADATA
shuke_ai-0.3.5.dist-info/WHEEL
shuke_ai-0.3.5.dist-info/entry_points.txt
shuke_ai-0.3.5.dist-info/top_level.txt
shuke_ai-0.3.5.dist-info/RECORD
