Metadata-Version: 2.4
Name: shuke-ai
Version: 0.3.5
Summary: 舒克AI工具集 - AI工具箱
Author-email: Chaiyapeng <your.email@example.com>
License-Expression: MIT
Classifier: Programming Language :: Python :: 3
Classifier: Operating System :: OS Independent
Requires-Python: >=3.8
Requires-Dist: PyQt6>=6.6.1
Requires-Dist: requests==2.31.0
Requires-Dist: urllib3==2.2.1
Requires-Dist: python-dotenv>=0.19.0
Requires-Dist: opencv-python>=4.6.0
Requires-Dist: pillow>=9.0.0
Requires-Dist: numpy>=1.21.0
Requires-Dist: setuptools>=45
